AUTHORS
LICENSE
MANIFEST.in
README.rst
setup.py
django_auth_policy/__init__.py
django_auth_policy/admin.py
django_auth_policy/apps.py
django_auth_policy/authentication.py
django_auth_policy/checks.py
django_auth_policy/decorators.py
django_auth_policy/forms.py
django_auth_policy/handlers.py
django_auth_policy/middleware.py
django_auth_policy/models.py
django_auth_policy/password_change.py
django_auth_policy/password_strength.py
django_auth_policy/settings.py
django_auth_policy/signals.py
django_auth_policy/user_admin.py
django_auth_policy.egg-info/PKG-INFO
django_auth_policy.egg-info/SOURCES.txt
django_auth_policy.egg-info/dependency_links.txt
django_auth_policy.egg-info/not-zip-safe
django_auth_policy.egg-info/pbr.json
django_auth_policy.egg-info/requires.txt
django_auth_policy.egg-info/top_level.txt
django_auth_policy/locale/fr/LC_MESSAGES/django.mo
django_auth_policy/locale/fr/LC_MESSAGES/django.po
django_auth_policy/locale/it/LC_MESSAGES/django.mo
django_auth_policy/locale/it/LC_MESSAGES/django.po
django_auth_policy/locale/nl/LC_MESSAGES/django.mo
django_auth_policy/locale/nl/LC_MESSAGES/django.po
django_auth_policy/management/__init__.py
django_auth_policy/management/commands/__init__.py
django_auth_policy/management/commands/filter_password_list.py
django_auth_policy/management/commands/unlock_all.py
django_auth_policy/migrations/0001_initial.py
django_auth_policy/migrations/0002_users_nullable.py
django_auth_policy/migrations/0003_auto_20150410_0408.py
django_auth_policy/migrations/0004_auto_20150422_0538.py
django_auth_policy/migrations/__init__.py
django_auth_policy/templates/admin/django_auth_policy/change_form.html
django_auth_policy/templates/admin/django_auth_policy/confirm_temporary_password.html
django_auth_policy/templates/admin/django_auth_policy/set_temporary_password.html
docs/index.rst