Metadata-Version: 1.1
Name: django-auth-policy
Version: 0.9.13
Summary: Enforces a couple of common authentication policies for the Django web framework.
Home-page: https://github.com/rudolphfroger/django-auth-policy
Author: Rudolph Froger
Author-email: rudolphfroger@dreamsolution.nl
License: BSD
Platform: UNKNOWN
Classifier: Development Status :: 3 - Alpha
Classifier: Environment :: Web Environment
Classifier: Intended Audience :: Developers
Classifier: License :: OSI Approved :: BSD License
Classifier: Operating System :: OS Independent
Classifier: Programming Language :: Python
Classifier: Framework :: Django
Classifier: Topic :: Security
Classifier: Topic :: Internet :: WWW/HTTP :: Session
Classifier: Topic :: Software Development :: Libraries :: Python Modules
